{"remainingRequest":"D:\\project\\Deecamp-project\\system\\Web\\node_modules\\ts-loader\\index.js??ref--4-1!D:\\project\\Deecamp-project\\system\\Web\\node_modules\\antd\\lib\\_util\\wave.js","dependencies":[{"path":"D:\\project\\Deecamp-project\\system\\Web\\node_modules\\antd\\lib\\_util\\wave.js","mtime":499162500000},{"path":"D:\\project\\Deecamp-project\\system\\Web\\node_modules\\cache-loader\\dist\\cjs.js","mtime":1595520254649},{"path":"D:\\project\\Deecamp-project\\system\\Web\\node_modules\\ts-loader\\index.js","mtime":1537906253000}],"contextDependencies":[],"result":["'use strict';\r\nObject.defineProperty(exports, \"__esModule\", {\r\n    value: true\r\n});\r\nvar _classCallCheck2 = require('babel-runtime/helpers/classCallCheck');\r\nvar _classCallCheck3 = _interopRequireDefault(_classCallCheck2);\r\nvar _createClass2 = require('babel-runtime/helpers/createClass');\r\nvar _createClass3 = _interopRequireDefault(_createClass2);\r\nvar _possibleConstructorReturn2 = require('babel-runtime/helpers/possibleConstructorReturn');\r\nvar _possibleConstructorReturn3 = _interopRequireDefault(_possibleConstructorReturn2);\r\nvar _inherits2 = require('babel-runtime/helpers/inherits');\r\nvar _inherits3 = _interopRequireDefault(_inherits2);\r\nvar _react = require('react');\r\nvar React = _interopRequireWildcard(_react);\r\nvar _reactDom = require('react-dom');\r\nvar _Event = require('css-animation/lib/Event');\r\nvar _Event2 = _interopRequireDefault(_Event);\r\nfunction _interopRequireWildcard(obj) { if (obj && obj.__esModule) {\r\n    return obj;\r\n}\r\nelse {\r\n    var newObj = {};\r\n    if (obj != null) {\r\n        for (var key in obj) {\r\n            if (Object.prototype.hasOwnProperty.call(obj, key))\r\n                newObj[key] = obj[key];\r\n        }\r\n    }\r\n    newObj['default'] = obj;\r\n    return newObj;\r\n} }\r\nfunction _interopRequireDefault(obj) { return obj && obj.__esModule ? obj : { 'default': obj }; }\r\nvar styleForPesudo = void 0;\r\nvar Wave = function (_React$Component) {\r\n    (0, _inherits3['default'])(Wave, _React$Component);\r\n    function Wave() {\r\n        (0, _classCallCheck3['default'])(this, Wave);\r\n        var _this = (0, _possibleConstructorReturn3['default'])(this, (Wave.__proto__ || Object.getPrototypeOf(Wave)).apply(this, arguments));\r\n        _this.onClick = function (node, waveColor) {\r\n            if (node.className.indexOf('-leave') >= 0) {\r\n                return;\r\n            }\r\n            var insertExtraNode = _this.props.insertExtraNode;\r\n            _this.extraNode = document.createElement('div');\r\n            var extraNode = _this.extraNode;\r\n            extraNode.className = 'ant-click-animating-node';\r\n            var attributeName = _this.getAttributeName();\r\n            node.removeAttribute(attributeName);\r\n            node.setAttribute(attributeName, 'true');\r\n            styleForPesudo = styleForPesudo || document.createElement('style');\r\n            if (waveColor && waveColor !== '#ffffff' && waveColor !== 'rgb(255, 255, 255)' && _this.isNotGrey(waveColor) && !/rgba\\(\\d*, \\d*, \\d*, 0\\)/.test(waveColor) &&\r\n                waveColor !== 'transparent') {\r\n                extraNode.style.borderColor = waveColor;\r\n                styleForPesudo.innerHTML = '[ant-click-animating-without-extra-node]:after { border-color: ' + waveColor + '; }';\r\n                if (!document.body.contains(styleForPesudo)) {\r\n                    document.body.appendChild(styleForPesudo);\r\n                }\r\n            }\r\n            if (insertExtraNode) {\r\n                node.appendChild(extraNode);\r\n            }\r\n            _Event2['default'].addEndEventListener(node, _this.onTransitionEnd);\r\n        };\r\n        _this.bindAnimationEvent = function (node) {\r\n            if (!node || !node.getAttribute || node.getAttribute('disabled') || node.className.indexOf('disabled') >= 0) {\r\n                return;\r\n            }\r\n            var onClick = function onClick(e) {\r\n                if (e.target.tagName === 'INPUT') {\r\n                    return;\r\n                }\r\n                _this.resetEffect(node);\r\n                var waveColor = getComputedStyle(node).getPropertyValue('border-top-color') ||\r\n                    getComputedStyle(node).getPropertyValue('border-color') || getComputedStyle(node).getPropertyValue('background-color');\r\n                _this.clickWaveTimeoutId = window.setTimeout(function () {\r\n                    return _this.onClick(node, waveColor);\r\n                }, 0);\r\n            };\r\n            node.addEventListener('click', onClick, true);\r\n            return {\r\n                cancel: function cancel() {\r\n                    node.removeEventListener('click', onClick, true);\r\n                }\r\n            };\r\n        };\r\n        _this.onTransitionEnd = function (e) {\r\n            if (!e || e.animationName !== 'fadeEffect') {\r\n                return;\r\n            }\r\n            _this.resetEffect(e.target);\r\n        };\r\n        return _this;\r\n    }\r\n    (0, _createClass3['default'])(Wave, [{\r\n            key: 'isNotGrey',\r\n            value: function isNotGrey(color) {\r\n                var match = (color || '').match(/rgba?\\((\\d*), (\\d*), (\\d*)(, [\\.\\d]*)?\\)/);\r\n                if (match && match[1] && match[2] && match[3]) {\r\n                    return !(match[1] === match[2] && match[2] === match[3]);\r\n                }\r\n                return true;\r\n            }\r\n        }, {\r\n            key: 'getAttributeName',\r\n            value: function getAttributeName() {\r\n                var insertExtraNode = this.props.insertExtraNode;\r\n                return insertExtraNode ? 'ant-click-animating' : 'ant-click-animating-without-extra-node';\r\n            }\r\n        }, {\r\n            key: 'resetEffect',\r\n            value: function resetEffect(node) {\r\n                if (!node || node === this.extraNode) {\r\n                    return;\r\n                }\r\n                var insertExtraNode = this.props.insertExtraNode;\r\n                var attributeName = this.getAttributeName();\r\n                node.removeAttribute(attributeName);\r\n                this.removeExtraStyleNode();\r\n                if (insertExtraNode && this.extraNode && node.contains(this.extraNode)) {\r\n                    node.removeChild(this.extraNode);\r\n                }\r\n                _Event2['default'].removeEndEventListener(node, this.onTransitionEnd);\r\n            }\r\n        }, {\r\n            key: 'removeExtraStyleNode',\r\n            value: function removeExtraStyleNode() {\r\n                if (styleForPesudo) {\r\n                    styleForPesudo.innerHTML = '';\r\n                }\r\n            }\r\n        }, {\r\n            key: 'componentDidMount',\r\n            value: function componentDidMount() {\r\n                this.instance = this.bindAnimationEvent((0, _reactDom.findDOMNode)(this));\r\n            }\r\n        }, {\r\n            key: 'componentWillUnmount',\r\n            value: function componentWillUnmount() {\r\n                if (this.instance) {\r\n                    this.instance.cancel();\r\n                }\r\n                if (this.clickWaveTimeoutId) {\r\n                    clearTimeout(this.clickWaveTimeoutId);\r\n                }\r\n            }\r\n        }, {\r\n            key: 'render',\r\n            value: function render() {\r\n                return this.props.children;\r\n            }\r\n        }]);\r\n    return Wave;\r\n}(React.Component);\r\nexports['default'] = Wave;\r\nmodule.exports = exports['default'];\r\n",{"version":3,"file":"D:\\project\\Deecamp-project\\system\\Web\\node_modules\\antd\\lib\\_util\\wave.js","sourceRoot":"","sources":["D:\\project\\Deecamp-project\\system\\Web\\node_modules\\antd\\lib\\_util\\wave.js"],"names":[],"mappings":"AAAA,YAAY,CAAC;AAEb,MAAM,CAAC,cAAc,CAAC,OAAO,EAAE,YAAY,EAAE;IACzC,KAAK,EAAE,IAAI;CACd,CAAC,CAAC;AAEH,IAAI,gBAAgB,GAAG,OAAO,CAAC,sCAAsC,CAAC,CAAC;AAEvE,IAAI,gBAAgB,GAAG,sBAAsB,CAAC,gBAAgB,CAAC,CAAC;AAEhE,IAAI,aAAa,GAAG,OAAO,CAAC,mCAAmC,CAAC,CAAC;AAEjE,IAAI,aAAa,GAAG,sBAAsB,CAAC,aAAa,CAAC,CAAC;AAE1D,IAAI,2BAA2B,GAAG,OAAO,CAAC,iDAAiD,CAAC,CAAC;AAE7F,IAAI,2BAA2B,GAAG,sBAAsB,CAAC,2BAA2B,CAAC,CAAC;AAEtF,IAAI,UAAU,GAAG,OAAO,CAAC,gCAAgC,CAAC,CAAC;AAE3D,IAAI,UAAU,GAAG,sBAAsB,CAAC,UAAU,CAAC,CAAC;AAEpD,IAAI,MAAM,GAAG,OAAO,CAAC,OAAO,CAAC,CAAC;AAE9B,IAAI,KAAK,GAAG,uBAAuB,CAAC,MAAM,CAAC,CAAC;AAE5C,IAAI,SAAS,GAAG,OAAO,CAAC,WAAW,CAAC,CAAC;AAErC,IAAI,MAAM,GAAG,OAAO,CAAC,yBAAyB,CAAC,CAAC;AAEhD,IAAI,OAAO,GAAG,sBAAsB,CAAC,MAAM,CAAC,CAAC;AAE7C,SAAS,uBAAuB,CAAC,GAAG,IAAI,IAAI,GAAG,IAAI,GAAG,CAAC,UAAU,EAAE;IAAE,OAAO,GAAG,CAAC;CAAE;KAAM;IAAE,IAAI,MAAM,GAAG,EAAE,CAAC;IAAC,IAAI,GAAG,IAAI,IAAI,EAAE;QAAE,KAAK,IAAI,GAAG,IAAI,GAAG,EAAE;YAAE,IAAI,MAAM,CAAC,SAAS,CAAC,cAAc,CAAC,IAAI,CAAC,GAAG,EAAE,GAAG,CAAC;gBAAE,MAAM,CAAC,GAAG,CAAC,GAAG,GAAG,CAAC,GAAG,CAAC,CAAC;SAAE;KAAE;IAAC,MAAM,CAAC,SAAS,CAAC,GAAG,GAAG,CAAC;IAAC,OAAO,MAAM,CAAC;CAAE,CAAC,CAAC;AAEhR,SAAS,sBAAsB,CAAC,GAAG,IAAI,OAAO,GAAG,IAAI,GAAG,CAAC,UAAU,CAAC,CAAC,CAAC,GAAG,CAAC,CAAC,CAAC,EAAE,SAAS,EAAE,GAAG,EAAE,CAAC,CAAC,CAAC;AAEjG,IAAI,cAAc,GAAG,KAAK,CAAC,CAAC;AAE5B,IAAI,IAAI,GAAG,UAAU,gBAAgB;IACjC,CAAC,CAAC,EAAE,UAAU,CAAC,SAAS,CAAC,CAAC,CAAC,IAAI,EAAE,gBAAgB,CAAC,CAAC;IAEnD,SAAS,IAAI;QACT,CAAC,CAAC,EAAE,gBAAgB,CAAC,SAAS,CAAC,CAAC,CAAC,IAAI,EAAE,IAAI,CAAC,CAAC;QAE7C,IAAI,KAAK,GAAG,CAAC,CAAC,EAAE,2BAA2B,CAAC,SAAS,CAAC,CAAC,CAAC,IAAI,EAAE,CAAC,IAAI,CAAC,SAAS,IAAI,MAAM,CAAC,cAAc,CAAC,IAAI,CAAC,CAAC,CAAC,KAAK,CAAC,IAAI,EAAE,SAAS,CAAC,CAAC,CAAC;QAEtI,KAAK,CAAC,OAAO,GAAG,UAAU,IAAI,EAAE,SAAS;YACrC,IAAI,IAAI,CAAC,SAAS,CAAC,OAAO,CAAC,QAAQ,CAAC,IAAI,CAAC,EAAE;gBACvC,OAAO;aACV;YACD,IAAI,eAAe,GAAG,KAAK,CAAC,KAAK,CAAC,eAAe,CAAC;YAElD,KAAK,CAAC,SAAS,GAAG,QAAQ,CAAC,aAAa,CAAC,KAAK,CAAC,CAAC;YAChD,IAAI,SAAS,GAAG,KAAK,CAAC,SAAS,CAAC;YAChC,SAAS,CAAC,SAAS,GAAG,0BAA0B,CAAC;YACjD,IAAI,aAAa,GAAG,KAAK,CAAC,gBAAgB,EAAE,CAAC;YAC7C,IAAI,CAAC,eAAe,CAAC,aAAa,CAAC,CAAC;YACpC,IAAI,CAAC,YAAY,CAAC,aAAa,EAAE,MAAM,CAAC,CAAC;YAEzC,cAAc,GAAG,cAAc,IAAI,QAAQ,CAAC,aAAa,CAAC,OAAO,CAAC,CAAC;YACnE,IAAI,SAAS,IAAI,SAAS,KAAK,SAAS,IAAI,SAAS,KAAK,oBAAoB,IAAI,KAAK,CAAC,SAAS,CAAC,SAAS,CAAC,IAAI,CAAC,0BAA0B,CAAC,IAAI,CAAC,SAAS,CAAC;gBAC3J,SAAS,KAAK,aAAa,EAAE;gBACzB,SAAS,CAAC,KAAK,CAAC,WAAW,GAAG,SAAS,CAAC;gBACxC,cAAc,CAAC,SAAS,GAAG,iEAAiE,GAAG,SAAS,GAAG,KAAK,CAAC;gBACjH,IAAI,CAAC,QAAQ,CAAC,IAAI,CAAC,QAAQ,CAAC,cAAc,CAAC,EAAE;oBACzC,QAAQ,CAAC,IAAI,CAAC,WAAW,CAAC,cAAc,CAAC,CAAC;iBAC7C;aACJ;YACD,IAAI,eAAe,EAAE;gBACjB,IAAI,CAAC,WAAW,CAAC,SAAS,CAAC,CAAC;aAC/B;YACD,OAAO,CAAC,SAAS,CAAC,CAAC,mBAAmB,CAAC,IAAI,EAAE,KAAK,CAAC,eAAe,CAAC,CAAC;QACxE,CAAC,CAAC;QACF,KAAK,CAAC,kBAAkB,GAAG,UAAU,IAAI;YACrC,IAAI,CAAC,IAAI,IAAI,CAAC,IAAI,CAAC,YAAY,IAAI,IAAI,CAAC,YAAY,CAAC,UAAU,CAAC,IAAI,IAAI,CAAC,SAAS,CAAC,OAAO,CAAC,UAAU,CAAC,IAAI,CAAC,EAAE;gBACzG,OAAO;aACV;YACD,IAAI,OAAO,GAAG,SAAS,OAAO,CAAC,CAAC;gBAE5B,IAAI,CAAC,CAAC,MAAM,CAAC,OAAO,KAAK,OAAO,EAAE;oBAC9B,OAAO;iBACV;gBACD,KAAK,CAAC,WAAW,CAAC,IAAI,CAAC,CAAC;gBAExB,IAAI,SAAS,GAAG,gBAAgB,CAAC,IAAI,CAAC,CAAC,gBAAgB,CAAC,kBAAkB,CAAC;oBAC3E,gBAAgB,CAAC,IAAI,CAAC,CAAC,gBAAgB,CAAC,cAAc,CAAC,IAAI,gBAAgB,CAAC,IAAI,CAAC,CAAC,gBAAgB,CAAC,kBAAkB,CAAC,CAAC;gBACvH,KAAK,CAAC,kBAAkB,GAAG,MAAM,CAAC,UAAU,CAAC;oBACzC,OAAO,KAAK,CAAC,OAAO,CAAC,IAAI,EAAE,SAAS,CAAC,CAAC;gBAC1C,CAAC,EAAE,CAAC,CAAC,CAAC;YACV,CAAC,CAAC;YACF,IAAI,CAAC,gBAAgB,CAAC,OAAO,EAAE,OAAO,EAAE,IAAI,CAAC,CAAC;YAC9C,OAAO;gBACH,MAAM,EAAE,SAAS,MAAM;oBACnB,IAAI,CAAC,mBAAmB,CAAC,OAAO,EAAE,OAAO,EAAE,IAAI,CAAC,CAAC;gBACrD,CAAC;aACJ,CAAC;QACN,CAAC,CAAC;QACF,KAAK,CAAC,eAAe,GAAG,UAAU,CAAC;YAC/B,IAAI,CAAC,CAAC,IAAI,CAAC,CAAC,aAAa,KAAK,YAAY,EAAE;gBACxC,OAAO;aACV;YACD,KAAK,CAAC,WAAW,CAAC,CAAC,CAAC,MAAM,CAAC,CAAC;QAChC,CAAC,CAAC;QACF,OAAO,KAAK,CAAC;IACjB,CAAC;IAED,CAAC,CAAC,EAAE,aAAa,CAAC,SAAS,CAAC,CAAC,CAAC,IAAI,EAAE,CAAC;YACjC,GAAG,EAAE,WAAW;YAChB,KAAK,EAAE,SAAS,SAAS,CAAC,KAAK;gBAC3B,IAAI,KAAK,GAAG,CAAC,KAAK,IAAI,EAAE,CAAC,CAAC,KAAK,CAAC,0CAA0C,CAAC,CAAC;gBAC5E,IAAI,KAAK,IAAI,KAAK,CAAC,CAAC,CAAC,IAAI,KAAK,CAAC,CAAC,CAAC,IAAI,KAAK,CAAC,CAAC,CAAC,EAAE;oBAC3C,OAAO,CAAC,CAAC,KAAK,CAAC,CAAC,CAAC,KAAK,KAAK,CAAC,CAAC,CAAC,IAAI,KAAK,CAAC,CAAC,CAAC,KAAK,KAAK,CAAC,CAAC,CAAC,CAAC,CAAC;iBAC5D;gBACD,OAAO,IAAI,CAAC;YAChB,CAAC;SACJ,EAAE;YACC,GAAG,EAAE,kBAAkB;YACvB,KAAK,EAAE,SAAS,gBAAgB;gBAC5B,IAAI,eAAe,GAAG,IAAI,CAAC,KAAK,CAAC,eAAe,CAAC;gBAEjD,OAAO,eAAe,CAAC,CAAC,CAAC,qBAAqB,CAAC,CAAC,CAAC,wCAAwC,CAAC;YAC9F,CAAC;SACJ,EAAE;YACC,GAAG,EAAE,aAAa;YAClB,KAAK,EAAE,SAAS,WAAW,CAAC,IAAI;gBAC5B,IAAI,CAAC,IAAI,IAAI,IAAI,KAAK,IAAI,CAAC,SAAS,EAAE;oBAClC,OAAO;iBACV;gBACD,IAAI,eAAe,GAAG,IAAI,CAAC,KAAK,CAAC,eAAe,CAAC;gBAEjD,IAAI,aAAa,GAAG,IAAI,CAAC,gBAAgB,EAAE,CAAC;gBAC5C,IAAI,CAAC,eAAe,CAAC,aAAa,CAAC,CAAC;gBACpC,IAAI,CAAC,oBAAoB,EAAE,CAAC;gBAC5B,IAAI,eAAe,IAAI,IAAI,CAAC,SAAS,IAAI,IAAI,CAAC,QAAQ,CAAC,IAAI,CAAC,SAAS,CAAC,EAAE;oBACpE,IAAI,CAAC,WAAW,CAAC,IAAI,CAAC,SAAS,CAAC,CAAC;iBACpC;gBACD,OAAO,CAAC,SAAS,CAAC,CAAC,sBAAsB,CAAC,IAAI,EAAE,IAAI,CAAC,eAAe,CAAC,CAAC;YAC1E,CAAC;SACJ,EAAE;YACC,GAAG,EAAE,sBAAsB;YAC3B,KAAK,EAAE,SAAS,oBAAoB;gBAChC,IAAI,cAAc,EAAE;oBAChB,cAAc,CAAC,SAAS,GAAG,EAAE,CAAC;iBACjC;YACL,CAAC;SACJ,EAAE;YACC,GAAG,EAAE,mBAAmB;YACxB,KAAK,EAAE,SAAS,iBAAiB;gBAC7B,IAAI,CAAC,QAAQ,GAAG,IAAI,CAAC,kBAAkB,CAAC,CAAC,CAAC,EAAE,SAAS,CAAC,WAAW,CAAC,CAAC,IAAI,CAAC,CAAC,CAAC;YAC9E,CAAC;SACJ,EAAE;YACC,GAAG,EAAE,sBAAsB;YAC3B,KAAK,EAAE,SAAS,oBAAoB;gBAChC,IAAI,IAAI,CAAC,QAAQ,EAAE;oBACf,IAAI,CAAC,QAAQ,CAAC,MAAM,EAAE,CAAC;iBAC1B;gBACD,IAAI,IAAI,CAAC,kBAAkB,EAAE;oBACzB,YAAY,CAAC,IAAI,CAAC,kBAAkB,CAAC,CAAC;iBACzC;YACL,CAAC;SACJ,EAAE;YACC,GAAG,EAAE,QAAQ;YACb,KAAK,EAAE,SAAS,MAAM;gBAClB,OAAO,IAAI,CAAC,KAAK,CAAC,QAAQ,CAAC;YAC/B,CAAC;SACJ,CAAC,CAAC,CAAC;IACJ,OAAO,IAAI,CAAC;AAChB,CAAC,CAAC,KAAK,CAAC,SAAS,CAAC,CAAC;AAEnB,OAAO,CAAC,SAAS,CAAC,GAAG,IAAI,CAAC;AAC1B,MAAM,CAAC,OAAO,GAAG,OAAO,CAAC,SAAS,CAAC,CAAC","sourcesContent":["'use strict';\n\nObject.defineProperty(exports, \"__esModule\", {\n    value: true\n});\n\nvar _classCallCheck2 = require('babel-runtime/helpers/classCallCheck');\n\nvar _classCallCheck3 = _interopRequireDefault(_classCallCheck2);\n\nvar _createClass2 = require('babel-runtime/helpers/createClass');\n\nvar _createClass3 = _interopRequireDefault(_createClass2);\n\nvar _possibleConstructorReturn2 = require('babel-runtime/helpers/possibleConstructorReturn');\n\nvar _possibleConstructorReturn3 = _interopRequireDefault(_possibleConstructorReturn2);\n\nvar _inherits2 = require('babel-runtime/helpers/inherits');\n\nvar _inherits3 = _interopRequireDefault(_inherits2);\n\nvar _react = require('react');\n\nvar React = _interopRequireWildcard(_react);\n\nvar _reactDom = require('react-dom');\n\nvar _Event = require('css-animation/lib/Event');\n\nvar _Event2 = _interopRequireDefault(_Event);\n\nfunction _interopRequireWildcard(obj) { if (obj && obj.__esModule) { return obj; } else { var newObj = {}; if (obj != null) { for (var key in obj) { if (Object.prototype.hasOwnProperty.call(obj, key)) newObj[key] = obj[key]; } } newObj['default'] = obj; return newObj; } }\n\nfunction _interopRequireDefault(obj) { return obj && obj.__esModule ? obj : { 'default': obj }; }\n\nvar styleForPesudo = void 0;\n\nvar Wave = function (_React$Component) {\n    (0, _inherits3['default'])(Wave, _React$Component);\n\n    function Wave() {\n        (0, _classCallCheck3['default'])(this, Wave);\n\n        var _this = (0, _possibleConstructorReturn3['default'])(this, (Wave.__proto__ || Object.getPrototypeOf(Wave)).apply(this, arguments));\n\n        _this.onClick = function (node, waveColor) {\n            if (node.className.indexOf('-leave') >= 0) {\n                return;\n            }\n            var insertExtraNode = _this.props.insertExtraNode;\n\n            _this.extraNode = document.createElement('div');\n            var extraNode = _this.extraNode;\n            extraNode.className = 'ant-click-animating-node';\n            var attributeName = _this.getAttributeName();\n            node.removeAttribute(attributeName);\n            node.setAttribute(attributeName, 'true');\n            // Not white or transparnt or grey\n            styleForPesudo = styleForPesudo || document.createElement('style');\n            if (waveColor && waveColor !== '#ffffff' && waveColor !== 'rgb(255, 255, 255)' && _this.isNotGrey(waveColor) && !/rgba\\(\\d*, \\d*, \\d*, 0\\)/.test(waveColor) && // any transparent rgba color\n            waveColor !== 'transparent') {\n                extraNode.style.borderColor = waveColor;\n                styleForPesudo.innerHTML = '[ant-click-animating-without-extra-node]:after { border-color: ' + waveColor + '; }';\n                if (!document.body.contains(styleForPesudo)) {\n                    document.body.appendChild(styleForPesudo);\n                }\n            }\n            if (insertExtraNode) {\n                node.appendChild(extraNode);\n            }\n            _Event2['default'].addEndEventListener(node, _this.onTransitionEnd);\n        };\n        _this.bindAnimationEvent = function (node) {\n            if (!node || !node.getAttribute || node.getAttribute('disabled') || node.className.indexOf('disabled') >= 0) {\n                return;\n            }\n            var onClick = function onClick(e) {\n                // Fix radio button click twice\n                if (e.target.tagName === 'INPUT') {\n                    return;\n                }\n                _this.resetEffect(node);\n                // Get wave color from target\n                var waveColor = getComputedStyle(node).getPropertyValue('border-top-color') || // Firefox Compatible\n                getComputedStyle(node).getPropertyValue('border-color') || getComputedStyle(node).getPropertyValue('background-color');\n                _this.clickWaveTimeoutId = window.setTimeout(function () {\n                    return _this.onClick(node, waveColor);\n                }, 0);\n            };\n            node.addEventListener('click', onClick, true);\n            return {\n                cancel: function cancel() {\n                    node.removeEventListener('click', onClick, true);\n                }\n            };\n        };\n        _this.onTransitionEnd = function (e) {\n            if (!e || e.animationName !== 'fadeEffect') {\n                return;\n            }\n            _this.resetEffect(e.target);\n        };\n        return _this;\n    }\n\n    (0, _createClass3['default'])(Wave, [{\n        key: 'isNotGrey',\n        value: function isNotGrey(color) {\n            var match = (color || '').match(/rgba?\\((\\d*), (\\d*), (\\d*)(, [\\.\\d]*)?\\)/);\n            if (match && match[1] && match[2] && match[3]) {\n                return !(match[1] === match[2] && match[2] === match[3]);\n            }\n            return true;\n        }\n    }, {\n        key: 'getAttributeName',\n        value: function getAttributeName() {\n            var insertExtraNode = this.props.insertExtraNode;\n\n            return insertExtraNode ? 'ant-click-animating' : 'ant-click-animating-without-extra-node';\n        }\n    }, {\n        key: 'resetEffect',\n        value: function resetEffect(node) {\n            if (!node || node === this.extraNode) {\n                return;\n            }\n            var insertExtraNode = this.props.insertExtraNode;\n\n            var attributeName = this.getAttributeName();\n            node.removeAttribute(attributeName);\n            this.removeExtraStyleNode();\n            if (insertExtraNode && this.extraNode && node.contains(this.extraNode)) {\n                node.removeChild(this.extraNode);\n            }\n            _Event2['default'].removeEndEventListener(node, this.onTransitionEnd);\n        }\n    }, {\n        key: 'removeExtraStyleNode',\n        value: function removeExtraStyleNode() {\n            if (styleForPesudo) {\n                styleForPesudo.innerHTML = '';\n            }\n        }\n    }, {\n        key: 'componentDidMount',\n        value: function componentDidMount() {\n            this.instance = this.bindAnimationEvent((0, _reactDom.findDOMNode)(this));\n        }\n    }, {\n        key: 'componentWillUnmount',\n        value: function componentWillUnmount() {\n            if (this.instance) {\n                this.instance.cancel();\n            }\n            if (this.clickWaveTimeoutId) {\n                clearTimeout(this.clickWaveTimeoutId);\n            }\n        }\n    }, {\n        key: 'render',\n        value: function render() {\n            return this.props.children;\n        }\n    }]);\n    return Wave;\n}(React.Component);\n\nexports['default'] = Wave;\nmodule.exports = exports['default'];"]}]}